README.rst
setup.py
repeaterbook_to_kml/__init__.py
repeaterbook_to_kml.egg-info/PKG-INFO
repeaterbook_to_kml.egg-info/SOURCES.txt
repeaterbook_to_kml.egg-info/dependency_links.txt
repeaterbook_to_kml.egg-info/entry_points.txt
repeaterbook_to_kml.egg-info/requires.txt
repeaterbook_to_kml.egg-info/top_level.txt