Metadata-Version: 1.1
Name: repeaterbook-to-kml
Version: 0.1
Summary: Convert CHIRP-Format CSV files exported from Repeaterbook into KML files
Home-page: https://github.com/coddingtonbear/repeaterbook-to-kml
Author: Adam Coddington
Author-email: me@adamcoddington.net
License: UNKNOWN
Platform: UNKNOWN
Classifier: License :: OSI Approved :: MIT License
Classifier: Operating System :: OS Independent
